enabledisablelua/LICENSE
enabledisablelua/README.MD
enabledisablelua/__init__.py
enabledisablelua/requirements.txt
enabledisablelua/thirdparty.json
enabledisablelua-0.10.dist-info/LICENSE.rst
enabledisablelua-0.10.dist-info/METADATA
enabledisablelua-0.10.dist-info/WHEEL
enabledisablelua-0.10.dist-info/top_level.txt
enabledisablelua-0.10.dist-info/RECORD
