Metadata-Version: 2.1
Name: enabledisablelua
Version: 0.10
Summary: Enables or disables User Account Control (UAC) on Windows
Home-page: https://github.com/hansalemaos/enabledisablelua
Author: Johannes Fischer
Author-email: <aulasparticularesdealemaosp@gmail.com>
License: MIT
Keywords: uac,admin,windows,lua,enable,disable
Classifier: Development Status :: 4 - Beta
Classifier: Programming Language :: Python :: 3 :: Only
Classifier: Programming Language :: Python :: 3.10
Classifier: Topic :: Scientific/Engineering :: Visualization
Classifier: Topic :: Software Development :: Libraries :: Python Modules
Classifier: Topic :: Utilities
License-File: LICENSE.rst
